[
    {
      "id": "AB12456",
      "name": "Scarlett Johansson",
      "email": "scarlettjohansson@gmail.com",
      "contact": "+919652358844",
      "organization": "XYZ organization",
      "roles": "Admin",
      "status": "Inactive"
    },
    {
      "id": "AB12457",
      "name": "Scarlett Johansson",
      "email": "scarlettjohansson@gmail.com",
      "contact": "+919652358844",
      "organization": "XYZ organization",
      "roles": "Admin",
      "status": "Inactive"
    },
    {
      "id": "AB12458",
      "name": "Scarlett Johansson",
      "email": "scarlettjohansson@gmail.com",
      "contact": "+919652358844",
      "organization": "XYZ organization",
      "roles": "Admin",
      "status": "Inactive"
    },
    {
      "id": "AB12459",
      "name": "Scarlett Johansson",
      "email": "scarlettjohansson@gmail.com",
      "contact": "+919652358844",
      "organization": "XYZ organization",
      "roles": "Admin",
      "status": "Inactive"
    },
    {
      "id": "AB124510",
      "name": "Scarlett Johansson",
      "email": "scarlettjohansson@gmail.com",
      "contact": "+919652358844",
      "organization": "XYZ organization",
      "roles": "Admin",
      "status": "Inactive"
    },
    {
      "id": "AB124511",
      "name": "Scarlett Johansson",
      "email": "scarlettjohansson@gmail.com",
      "contact": "+919652358844",
      "organization": "XYZ organization",
      "roles": "Admin",
      "status": "Inactive"
    },
    {
      "id": "AB124512",
      "name": "Scarlett Johansson",
      "email": "scarlettjohansson@gmail.com",
      "contact": "+919652358844",
      "organization": "XYZ organization",
      "roles": "Admin",
      "status": "Inactive"
    },
    {
      "id": "AB124513",
      "name": "Scarlett Johansson",
      "email": "scarlettjohansson@gmail.com",
      "contact": "+919652358844",
      "organization": "XYZ organization",
      "roles": "Admin",
      "status": "Inactive"
    },
    {
      "id": "AB124514",
      "name": "Scarlett Johansson",
      "email": "scarlettjohansson@gmail.com",
      "contact": "+919652358844",
      "organization": "XYZ organization",
      "roles": "Admin",
      "status": "Inactive"
    },
    {
      "id": "789",
      "name": "yamuna",
      "email": "scarlettjohansson@gmail.com",
      "contact": "+919652358844",
      "organization": "yamuna organization",
      "roles": "employee",
      "status": "active"
    }
  ]
  